ptr.py
ptr-26.1.23.dist-info/licenses/LICENSE
ptr-26.1.23.dist-info/METADATA
ptr-26.1.23.dist-info/WHEEL
ptr-26.1.23.dist-info/entry_points.txt
ptr-26.1.23.dist-info/top_level.txt
ptr-26.1.23.dist-info/RECORD
