Metadata-Version: 2.4
Name: ptr
Version: 26.1.23
Summary: Parallel asyncio Python setup.(cfg|py) Test Runner
Author-email: Cooper Lees <me@cooperlees.com>
License: MIT
Project-URL: Homepage, http://github.com/cooperlees/ptr
Classifier: Development Status :: 3 - Alpha
Classifier: License :: OSI Approved :: MIT License
Classifier: Programming Language :: Python :: 3
Classifier: Programming Language :: Python :: 3 :: Only
Classifier: Programming Language :: Python :: 3.10
Classifier: Programming Language :: Python :: 3.11
Classifier: Programming Language :: Python :: 3.12
Classifier: Programming Language :: Python :: 3.13
Classifier: Programming Language :: Python :: 3.14
Requires-Python: >=3.10
License-File: LICENSE
Requires-Dist: tomli>=1.1.0; python_full_version < "3.11.0a7"
Dynamic: license-file
